{
  "case_docket_label": "US District Court Criminal Docket",
  "case_file_name": "US.DIS.OHN_103mj9093_ohnd",
  "case_key": "1:03mj9093_ohnd",
  "case_lni": "7WBN-JH90-Y892-B0C6-00000-00",
  "case_number": "1:03mj9093",
  "case_title": "United States of America v. USA",
  "case_info_full_case_name": "United States of America v. USA",
  "case_info_short_case_name": "United States of America",
  "case_info_party1": "United States of America",
  "case_info_party2": "USA",
  "case_date_filed": "2003-12-24",
  "case_status": "Open",
  "case_status_date": null,
  "case_type_description": "Criminal",
  "attorneys": [
    {
      "attorney_label": "[COR LD NTC]"
    }
  ],
  "parties": [
    {
      "party_description": "Defendant",
      "charges": [
        {
          "charge_description": "Attempt to kill an employee of the United States"
        }
      ],
      "judges": [
        {
          "judge_title": "Magistrate Judge",
          "judge_name": "William H. Baughman, Jr.",
          "judge_guid": "urn:entity:jud-100062083"
        }
      ]
    },
    {
      "party_name": "Aubrey A. Waller",
      "party_description": "Defendant"
    }
  ]
}