{
  "case_docket_label": "US District Court Criminal Docket",
  "case_file_name": "US.DIS.IAN_503m4030_iand",
  "case_key": "5:03m4030_iand",
  "case_lni": "7WBN-S9G0-Y892-B3XV-00000-00",
  "case_number": "5:03m4030",
  "case_title": "USA v. Sandoval",
  "case_info_full_case_name": "USA v. Sandoval",
  "case_info_short_case_name": "USA",
  "case_info_party1": "USA",
  "case_info_party2": "Sandoval",
  "case_date_filed": "2003-05-06",
  "case_status": "Open",
  "case_status_date": null,
  "case_type_description": "Criminal",
  "attorneys": [
    {
      "attorney_label": "[COR LD NTC]"
    }
  ],
  "parties": [
    {
      "party_description": "Defendant",
      "judges": [
        {
          "judge_title": "Magistrate Judge",
          "judge_name": "Paul A Zoss",
          "judge_guid": "urn:entity:jud-100016377"
        }
      ]
    }
  ]
}