{
  "case_docket_label": "US District Court Criminal Docket",
  "case_file_name": "US.DIS.NCW_398m117_ncwd",
  "case_key": "3:98m117_ncwd",
  "case_lni": "7WBN-HGM0-Y892-B0TW-00000-00",
  "case_number": "3:98m117",
  "case_title": "USA v. Sld Dft 3:98M117",
  "case_info_full_case_name": "USA v. Sld Dft 3:98M117",
  "case_info_short_case_name": "USA",
  "case_info_party1": "USA",
  "case_info_party2": "Sld Dft 3:98M117",
  "case_date_filed": "1998-06-18",
  "case_status": "Open",
  "case_status_date": null,
  "case_type_description": "Criminal",
  "attorneys": [
    {
      "attorney_name": "NONE",
      "attorney_label": "[NO LABEL]"
    }
  ],
  "parties": [
    {
      "party_name": "SLD DFT 3:98M117",
      "party_description": "Defendant",
      "judges": [
        {
          "judge_title": "Magistrate Judge",
          "judge_name": "Carl Horn, III",
          "judge_guid": "urn:entity:jud-100094874"
        }
      ]
    }
  ]
}