{
  "case_docket_label": "US District Court Criminal Docket",
  "case_file_name": "US.DIS.TXW_219mj8446_TXWD",
  "case_key": "2:19mj8446_TXWD",
  "case_lni": "5X16-RTY1-J9YR-S4X6-00000-00",
  "case_number": "2:19mj8446",
  "case_title": "USA v. Mendoza-Chavez",
  "case_info_full_case_name": "USA v. Mendoza-Chavez",
  "case_info_short_case_name": "USA",
  "case_info_party1": "USA",
  "case_info_party2": "Mendoza-Chavez",
  "case_date_filed": "2019-09-11",
  "case_status": "Open",
  "case_status_date": null,
  "case_type_description": "Criminal",
  "parties": [
    {
      "party_name": "Gustavo Mendoza-Chavez",
      "party_description": "Defendant",
      "charges": [
        {
          "charge_description": "8 USC 1326(a)(1) Re-entry after deportation from the United States"
        },
        {
          "charge_offence_description": "8 USC 1326(a)(1) Re-entry after deportation from t"
        }
      ],
      "judges": [
        {
          "judge_title": "Judge",
          "judge_name": "Collis White",
          "judge_guid": "urn:entity:jud-100022858"
        }
      ]
    }
  ]
}