{
  "case_docket_label": "US District Court Criminal Docket",
  "case_file_name": "US.DIS.ILN_00CR584_ILND",
  "case_key": "00CR584_ILND",
  "case_lni": "7Y4B-BBH0-Y892-B216-00000-00",
  "case_number": "00CR584",
  "case_title": "United States of America v. Moro et al",
  "case_info_full_case_name": "United States of America v. Moro et al",
  "case_info_short_case_name": "United States of America",
  "case_info_party1": "United States of America",
  "case_info_party2": "Moro et al",
  "case_date_filed": "2000-07-25",
  "case_status": "Closed",
  "case_status_date": null,
  "case_type_description": "Criminal",
  "attorneys": [
    {
      "attorney_label": "Lead Attorney"
    },
    {},
    {
      "attorney_name": "Probation Department"
    }
  ],
  "parties": [
    {
      "party_name": "Angelo Moro",
      "party_description": "Defendant",
      "charges": [
        {
          "charge_statute": "18:1962 3300.F"
        },
        {
          "charge_description": "18:1962 3300.F Interstate Commerce (1)"
        },
        {
          "charge_offence_description": "Felony",
          "charge_offence_level": "4"
        },
        {
          "charge_statute": "18:371.F"
        },
        {
          "charge_description": "18:371.F Conspiracy to Defraud The United States And 18:2 Aid And Abet (2)"
        },
        {
          "charge_offence_description": "Felony",
          "charge_offence_level": "4"
        },
        {
          "charge_statute": "18:2314.F"
        },
        {
          "charge_description": "18:2314.F Scheme to Defraud: Money, State Tax Stamps (3)"
        },
        {
          "charge_offence_description": "Felony",
          "charge_offence_level": "4"
        },
        {
          "charge_statute": "18:2314.F"
        },
        {
          "charge_description": "18:2314.F Scheme to Defraud: Money, State Tax Stamps And 18:2 Aid And Abet (4)"
        },
        {
          "charge_offence_description": "Felony",
          "charge_offence_level": "4"
        },
        {
          "charge_statute": "18:2314.F"
        },
        {
          "charge_description": "18:2314.F Scheme to Defraud: Money, State Tax Stamps And 18:2 Aid And Abet (5)"
        },
        {
          "charge_offence_description": "Felony",
          "charge_offence_level": "4"
        },
        {
          "charge_statute": "18:2314.F"
        },
        {
          "charge_description": "18:2314.F Scheme to Defraud: Money, State Tax Stamps And 18:2 Aid And Abet (6)"
        },
        {
          "charge_offence_description": "Felony",
          "charge_offence_level": "4"
        },
        {
          "charge_statute": "18:2314.F"
        },
        {
          "charge_description": "18:2314.F Scheme to Defraud: Money, State Tax Stamps And 18:2 Aid And Abet (7)"
        },
        {
          "charge_offence_description": "Felony",
          "charge_offence_level": "4"
        },
        {
          "charge_statute": "26:7206C.F"
        },
        {
          "charge_description": "26:7206C.F Declare Under Penalty of Perjury (8-10)"
        },
        {
          "charge_offence_description": "Felony",
          "charge_offence_level": "4"
        }
      ]
    },
    {
      "party_name": "Sali Moro",
      "party_description": "Defendant",
      "charges": [
        {
          "charge_statute": "18:1962 3300.F"
        },
        {
          "charge_description": "18:1962 3300.F Interstate Commerce (1)"
        },
        {
          "charge_offence_description": "Felony",
          "charge_offence_level": "4"
        },
        {
          "charge_statute": "18:371.F"
        },
        {
          "charge_description": "18:371.F Conspiracy to Defraud The United States And 18:2 Aid And Abet (2)"
        },
        {
          "charge_offence_description": "Felony",
          "charge_offence_level": "4"
        },
        {
          "charge_statute": "18:2314.F"
        },
        {
          "charge_description": "18:2314.F Scheme to Defraud: Money, State Tax Stamps (3)"
        },
        {
          "charge_offence_description": "Felony",
          "charge_offence_level": "4"
        },
        {
          "charge_statute": "18:2314.F"
        },
        {
          "charge_description": "18:2314.F Scheme to Defraud: Money, State Tax Stamps And 18:2 Aid And Abet (4)"
        },
        {
          "charge_offence_description": "Felony",
          "charge_offence_level": "4"
        },
        {
          "charge_statute": "18:2314.F"
        },
        {
          "charge_description": "18:2314.F Scheme to Defraud: Money, State Tax Stamps And 18:2 Aid And Abet (5)"
        },
        {
          "charge_offence_description": "Felony",
          "charge_offence_level": "4"
        },
        {
          "charge_statute": "18:2314.F"
        },
        {
          "charge_description": "18:2314.F Scheme to Defraud: Money, State Tax Stamps And 18:2 Aid And Abet (6)"
        },
        {
          "charge_offence_description": "Felony",
          "charge_offence_level": "4"
        },
        {
          "charge_statute": "18:2314.F"
        },
        {
          "charge_description": "18:2314.F Scheme to Defraud: Money, State Tax Stamps And 18:2 Aid And Abet (7)"
        },
        {
          "charge_offence_description": "Felony",
          "charge_offence_level": "4"
        }
      ]
    },
    {
      "party_name": "John Dragan Moro",
      "party_description": "Defendant",
      "charges": [
        {
          "charge_statute": "18:1962 3300.F"
        },
        {
          "charge_description": "18:1962 3300.F Interstate Commerce (1)"
        },
        {
          "charge_disposition": "The Defendant is Hereby Committed to The Custody of The United States Bureau of Prisons to be Imprisoned For A Total Term of Thirty-Seven (37) Months on Count 1 of The Indictment. The Defendant is Remanded to The Custody of The United States Marshal. Upon Release From Imprisonment, The Defendant Shall be on Supervised Release For A Term of Two (2) Years on Count 1 of The Indictment. The Court Waives Fine And Costs of Incarceration. The Defendant Shall Make Total Restitution in The Amount of $114,550.00. Schedule of Payments."
        },
        {
          "charge_offence_description": "Felony",
          "charge_offence_level": "4"
        },
        {
          "charge_statute": "18:371.F"
        },
        {
          "charge_description": "18:371.F Conspiracy to Defraud The United States And 18:2 Aid And Abet (2)"
        },
        {
          "charge_disposition": "Remaining Counts Are Dismissed on The Motion of The United States."
        },
        {
          "charge_offence_description": "Felony",
          "charge_offence_level": "4"
        },
        {
          "charge_statute": "18:2314.F"
        },
        {
          "charge_description": "18:2314.F Scheme to Defraud: Money, State Tax Stamps (3)"
        },
        {
          "charge_disposition": "Remaining Counts Are Dismissed on The Motion of The United States."
        },
        {
          "charge_offence_description": "Felony",
          "charge_offence_level": "4"
        },
        {
          "charge_statute": "18:2314.F"
        },
        {
          "charge_description": "18:2314.F Scheme to Defraud: Money, State Tax Stamps And 18:2 Aid And Abet (5)"
        },
        {
          "charge_disposition": "Remaining Counts Are Dismissed on The Motion of The United States."
        },
        {
          "charge_offence_description": "Felony",
          "charge_offence_level": "4"
        },
        {
          "charge_statute": "18:2314.F"
        },
        {
          "charge_description": "18:2314.F Scheme to Defraud: Money, State Tax Stamps And 18:2 Aid And Abet (6)"
        },
        {
          "charge_disposition": "Remaining Counts Are Dismissed on The Motion of The United States."
        },
        {
          "charge_offence_description": "Felony",
          "charge_offence_level": "4"
        }
      ],
      "judges": [
        {
          "judge_title": "Honorable",
          "judge_name": "James F Holderman",
          "judge_guid": "urn:entity:jud-100051386"
        }
      ]
    },
    {
      "party_name": "Julie Moro",
      "party_description": "Defendant",
      "charges": [
        {
          "charge_statute": "18:1962 3300.F"
        },
        {
          "charge_description": "18:1962 3300.F Interstate Commerce (1)"
        },
        {
          "charge_offence_description": "Felony",
          "charge_offence_level": "4"
        },
        {
          "charge_statute": "18:371.F"
        },
        {
          "charge_description": "18:371.F Conspiracy to Defraud The United States And 18:2 Aid And Abet (2)"
        },
        {
          "charge_offence_description": "Felony",
          "charge_offence_level": "4"
        },
        {
          "charge_statute": "18:2314.F"
        },
        {
          "charge_description": "18:2314.F Scheme to Defraud: Money, State Tax Stamps (3)"
        },
        {
          "charge_offence_description": "Felony",
          "charge_offence_level": "4"
        },
        {
          "charge_statute": "18:2314.F"
        },
        {
          "charge_description": "18:2314.F Scheme to Defraud: Money, State Tax Stamps And 18:2 Aid And Abet (6)"
        },
        {
          "charge_offence_description": "Felony",
          "charge_offence_level": "4"
        },
        {
          "charge_statute": "18:2314.F"
        },
        {
          "charge_description": "18:2314.F Scheme to Defraud: Money, State Tax Stamps And 18:2 Aid And Abet (7)"
        },
        {
          "charge_offence_description": "Felony",
          "charge_offence_level": "4"
        }
      ]
    },
    {
      "party_name": "Maria Djenisov",
      "party_description": "Defendant",
      "charges": [
        {
          "charge_statute": "18:1962 3300.F"
        },
        {
          "charge_description": "18:1962 3300.F Interstate Commerce (1)"
        },
        {
          "charge_offence_description": "Felony",
          "charge_offence_level": "4"
        },
        {
          "charge_statute": "18:371.F"
        },
        {
          "charge_description": "18:371.F Conspiracy to Defraud The United States And 18:2 Aid And Abet (2)"
        },
        {
          "charge_offence_description": "Felony",
          "charge_offence_level": "4"
        },
        {
          "charge_statute": "18:2314.F"
        },
        {
          "charge_description": "18:2314.F Scheme to Defraud: Money, State Tax Stamps (3)"
        },
        {
          "charge_offence_description": "Felony",
          "charge_offence_level": "4"
        },
        {
          "charge_statute": "18:2314.F"
        },
        {
          "charge_description": "18:2314.F Scheme to Defraud: Money, State Tax Stamps And 18:2 Aid And Abet (4)"
        },
        {
          "charge_offence_description": "Felony",
          "charge_offence_level": "4"
        },
        {
          "charge_statute": "18:2314.F"
        },
        {
          "charge_description": "18:2314.F Scheme to Defraud: Money, State Tax Stamps And 18:2 Aid And Abet (5)"
        },
        {
          "charge_offence_description": "Felony",
          "charge_offence_level": "4"
        },
        {
          "charge_statute": "18:2314.F"
        },
        {
          "charge_description": "18:2314.F Scheme to Defraud: Money, State Tax Stamps And 18:2 Aid And Abet (6)"
        },
        {
          "charge_offence_description": "Felony",
          "charge_offence_level": "4"
        },
        {
          "charge_statute": "18:2314.F"
        },
        {
          "charge_description": "18:2314.F Scheme to Defraud: Money, State Tax Stamps And 18:2 Aid And Abet (7)"
        },
        {
          "charge_offence_description": "Felony",
          "charge_offence_level": "4"
        }
      ]
    },
    {
      "party_name": "Helen Moro",
      "party_description": "Defendant",
      "charges": [
        {
          "charge_statute": "18:1962 3300.F"
        },
        {
          "charge_description": "18:1962 3300.F Interstate Commerce (1)"
        },
        {
          "charge_disposition": "The Defendant is Hereby Committed to The Custody of The United States Bureau of Prisons to be Imprisoned For A Total Term of Fifteen (15) Months on Count 1 of The Indictment. The Defendant is Remanded to The Custody of The United States Marshal. Upon Release From Imprisonment, The Defendant Shall be on Supervised Release For A Term of Three (3) Years on Count 1 of The Indictment. The Defendant Shall Make Total Restitution in The Amount of $102,723.00. Schedule of Payments."
        },
        {
          "charge_offence_description": "Felony",
          "charge_offence_level": "4"
        },
        {
          "charge_statute": "18:371.F"
        },
        {
          "charge_description": "18:371.F Conspiracy to Defraud The United States And 18:2 Aid And Abet (2)"
        },
        {
          "charge_disposition": "Remaining Counts Are Dismissed on The Motion of The United States."
        },
        {
          "charge_offence_description": "Felony",
          "charge_offence_level": "4"
        },
        {
          "charge_statute": "18:2314.F"
        },
        {
          "charge_description": "18:2314.F Scheme to Defraud: Money, State Tax Stamps (3)"
        },
        {
          "charge_disposition": "Remaining Counts Are Dismissed on The Motion of The United States."
        },
        {
          "charge_offence_description": "Felony",
          "charge_offence_level": "4"
        },
        {
          "charge_statute": "18:2314.F"
        },
        {
          "charge_description": "18:2314.F Scheme to Defraud: Money, State Tax Stamps And 18:2 Aid And Abet (5)"
        },
        {
          "charge_disposition": "Remaining Counts Are Dismissed on The Motion of The United States."
        },
        {
          "charge_offence_description": "Felony",
          "charge_offence_level": "4"
        },
        {
          "charge_statute": "18:2314.F"
        },
        {
          "charge_description": "18:2314.F Scheme to Defraud: Money, State Tax Stamps And 18:2 Aid And Abet (7)"
        },
        {
          "charge_disposition": "Remaining Counts Are Dismissed on The Motion of The United States."
        },
        {
          "charge_offence_description": "Felony",
          "charge_offence_level": "4"
        }
      ],
      "judges": [
        {
          "judge_title": "Honorable",
          "judge_name": "James F Holderman",
          "judge_guid": "urn:entity:jud-100051386"
        },
        {
          "judge_title": "Honorable",
          "judge_name": "Arlander Keys",
          "judge_guid": "urn:entity:jud-100040469"
        }
      ]
    },
    {
      "party_name": "Aranka Moro",
      "party_description": "Defendant",
      "charges": [
        {
          "charge_statute": "18:1962 3300.F"
        },
        {
          "charge_description": "18:1962 3300.F Interstate Commerce (1)"
        },
        {
          "charge_offence_description": "Felony",
          "charge_offence_level": "4"
        },
        {
          "charge_statute": "18:371.F"
        },
        {
          "charge_description": "18:371.F Conspiracy to Defraud The United States And 18:2 Aid And Abet (2)"
        },
        {
          "charge_offence_description": "Felony",
          "charge_offence_level": "4"
        },
        {
          "charge_statute": "18:2314.F"
        },
        {
          "charge_description": "18:2314.F Scheme to Defraud: Money, State Tax Stamps And 18:2 Aid And Abet (5)"
        },
        {
          "charge_offence_description": "Felony",
          "charge_offence_level": "4"
        },
        {
          "charge_statute": "18:2314.F"
        },
        {
          "charge_description": "18:2314.F Scheme to Defraud: Money, State Tax Stamps And 18:2 Aid And Abet (6)"
        },
        {
          "charge_offence_description": "Felony",
          "charge_offence_level": "4"
        },
        {
          "charge_statute": "18:2314.F"
        },
        {
          "charge_description": "18:2314.F Scheme to Defraud: Money, State Tax Stamps And 18:2 Aid And Abet (7)"
        },
        {
          "charge_offence_description": "Felony",
          "charge_offence_level": "4"
        }
      ]
    }
  ]
}