{
  "case_docket_label": "US District Court Criminal Docket",
  "case_file_name": "US.DIS.AZ_295pt46_azd",
  "case_key": "2:95pt46_azd",
  "case_lni": "7WBN-H0W0-Y892-B2ND-00000-00",
  "case_number": "2:95pt46",
  "case_title": "USA v. Stanard",
  "case_info_full_case_name": "USA v. Stanard",
  "case_info_short_case_name": "USA",
  "case_info_party1": "USA",
  "case_info_party2": "Stanard",
  "case_date_filed": "1995-06-19",
  "case_status": "Open",
  "case_status_date": null,
  "case_type_description": "Criminal",
  "attorneys": [
    {
      "attorney_name": "NONE",
      "attorney_label": "[NO LABEL]"
    }
  ],
  "parties": [
    {
      "party_name": "STEVEN R STANARD",
      "party_description": "Defendant",
      "charges": [
        {
          "charge_description": "in Violation of Wire Fraud"
        }
      ],
      "judges": [
        {
          "judge_title": "Judge",
          "judge_name": "Stephen M McNamee",
          "judge_guid": "urn:entity:jud-100065660"
        }
      ]
    }
  ]
}