{
  "case_docket_label": "US District Court Criminal Docket",
  "case_file_name": "US.DIS.TXS_717mj587_TXSD",
  "case_key": "7:17mj587_TXSD",
  "case_lni": "5N7F-6N31-DXDT-G0KJ-00000-00",
  "case_number": "7:17mj587",
  "case_title": "USA v. Perez-Miramontes",
  "case_info_full_case_name": "USA v. Perez-Miramontes",
  "case_info_short_case_name": "USA",
  "case_info_party1": "USA",
  "case_info_party2": "Perez-Miramontes",
  "case_date_filed": "2017-04-03",
  "case_status": "Open",
  "case_status_date": null,
  "case_type_description": "Criminal",
  "parties": [
    {
      "party_name": "Claudio Perez-Miramontes",
      "party_description": "Defendant",
      "charges": [
        {
          "charge_description": "8:1326.F"
        },
        {
          "charge_offence_description": "8:1326.F"
        }
      ],
      "judges": [
        {
          "judge_title": "Magistrate Judge",
          "judge_name": "Peter E Ormsby",
          "judge_guid": "urn:entity:jud-100025379"
        }
      ]
    }
  ]
}