{
  "case_docket_label": "US District Court Criminal Docket",
  "case_file_name": "US.DIS.TXS_408cr123_TXSD",
  "case_key": "4:08cr123_TXSD",
  "case_lni": "7WBN-S4R0-Y892-B01M-00000-00",
  "case_number": "4:08cr123",
  "case_title": "USA v. Eslava-Torres",
  "case_info_full_case_name": "USA v. Eslava-Torres",
  "case_info_short_case_name": "USA",
  "case_info_party1": "USA",
  "case_info_party2": "Eslava-Torres",
  "case_date_filed": "2008-03-10",
  "case_status": "Open",
  "case_status_date": null,
  "case_type_description": "Criminal",
  "attorneys": [
    {
      "attorney_label": "[COR LD NTC]"
    },
    {
      "attorney_name": "Financial Litigation",
      "attorney_label": "[COR LD NTC]"
    },
    {
      "attorney_label": "[COR LD NTC]"
    },
    {
      "attorney_name": "US Pretrial Svcs - H",
      "attorney_label": "[COR LD NTC]"
    },
    {
      "attorney_name": "US Probation - H",
      "attorney_label": "[COR LD NTC]"
    }
  ],
  "parties": [
    {
      "party_name": "Carlos Eslava-Torres",
      "party_description": "Defendant",
      "charges": [
        {
          "charge_description": "ILLEGAL REENTRY AFTER DEPORTATION (1)"
        },
        {
          "charge_offence_description": "Opening",
          "charge_offence_level": "4"
        }
      ],
      "judges": [
        {
          "judge_title": "Judge",
          "judge_name": "Gray H. Miller",
          "judge_guid": "urn:entity:jud-100036212"
        }
      ]
    }
  ]
}